dacp/__init__.py
dacp/api.py
dacp/cli.py
dacp/exceptions.py
dacp/intelligence.py
dacp/json_parser.py
dacp/llm.py
dacp/logging_config.py
dacp/main.py
dacp/orchestrator.py
dacp/protocol.py
dacp/tools.py
dacp/types.py
dacp/workflow.py
dacp/workflow_runtime.py
dacp-0.3.5.dist-info/licenses/LICENSE
dacp-0.3.5.dist-info/METADATA
dacp-0.3.5.dist-info/WHEEL
dacp-0.3.5.dist-info/entry_points.txt
dacp-0.3.5.dist-info/top_level.txt
dacp-0.3.5.dist-info/RECORD
